{
  "lang":"pt",
  "name":"pipeline",
  "version":"0.0.0",
  "spacy_version":">=3.8.7,<3.9.0",
  "description":"",
  "author":"",
  "email":"",
  "url":"",
  "license":"",
  "spacy_git_version":"4b65aa7",
  "vectors":{
    "width":0,
    "vectors":0,
    "keys":0,
    "name":null,
    "mode":"default"
  },
  "labels":{
    "tok2vec":[

    ],
    "ner":[
      "OPERADORA"
    ]
  },
  "pipeline":[
    "tok2vec",
    "ner"
  ],
  "components":[
    "tok2vec",
    "ner"
  ],
  "disabled":[

  ],
  "performance":{
    "ents_f":0.9434546863,
    "ents_p":0.9485981308,
    "ents_r":0.938366718,
    "ents_per_type":{
      "OPERADORA":{
        "p":0.9485981308,
        "r":0.938366718,
        "f":0.9434546863
      }
    },
    "tok2vec_loss":12.8696066923,
    "ner_loss":2.1838760376
  }
}